rowboat/__init__.py
rowboat/client.py
rowboat/schema.py
rowboat-5.0.1.dist-info/METADATA
rowboat-5.0.1.dist-info/WHEEL
rowboat-5.0.1.dist-info/RECORD
