Metadata-Version: 2.4
Name: rowboat
Version: 5.0.1
Summary: Python sdk for the Rowboat API
Project-URL: Homepage, https://github.com/rowboatlabs/rowboat/tree/main/apps/python-sdk
Project-URL: Bug Tracker, https://github.com/rowboatlabs/rowboat/issues
Author-email: Ramnique Singh <ramnique@rowboatlabs.com>
Classifier: License :: OSI Approved :: Apache Software License
Classifier: Operating System :: OS Independent
Classifier: Programming Language :: Python :: 3
Requires-Python: >=3.7
Requires-Dist: pydantic>=2.0.0
Requires-Dist: requests>=2.25.0
